rlgym_learn_algos/__init__.py
rlgym_learn_algos/conversion/__init__.py
rlgym_learn_algos/conversion/convert_rlgym_ppo_checkpoint.py
rlgym_learn_algos/logging/__init__.py
rlgym_learn_algos/logging/dict_metrics_logger.py
rlgym_learn_algos/logging/metrics_logger.py
rlgym_learn_algos/logging/wandb_metrics_logger.py
rlgym_learn_algos/ppo/__init__.py
rlgym_learn_algos/ppo/actor.py
rlgym_learn_algos/ppo/basic_critic.py
rlgym_learn_algos/ppo/continuous_actor.py
rlgym_learn_algos/ppo/critic.py
rlgym_learn_algos/ppo/discrete_actor.py
rlgym_learn_algos/ppo/env_trajectories.py
rlgym_learn_algos/ppo/experience_buffer.py
rlgym_learn_algos/ppo/experience_buffer_numpy.py
rlgym_learn_algos/ppo/gae_trajectory_processor.py
rlgym_learn_algos/ppo/gae_trajectory_processor_pure_python.py
rlgym_learn_algos/ppo/multi_discrete_actor.py
rlgym_learn_algos/ppo/ppo_agent_controller.py
rlgym_learn_algos/ppo/ppo_learner.py
rlgym_learn_algos/ppo/ppo_metrics_logger.py
rlgym_learn_algos/ppo/trajectory.py
rlgym_learn_algos/ppo/trajectory_processor.py
rlgym_learn_algos/py.typed
rlgym_learn_algos/rlgym_learn_algos.cpython-310-darwin.so
rlgym_learn_algos/rlgym_learn_algos.pyi
rlgym_learn_algos/stateful_functions/__init__.py
rlgym_learn_algos/stateful_functions/batch_reward_type_numpy_converter.py
rlgym_learn_algos/stateful_functions/numpy_obs_standardizer.py
rlgym_learn_algos/stateful_functions/obs_standardizer.py
rlgym_learn_algos/util/__init__.py
rlgym_learn_algos/util/running_stats.py
rlgym_learn_algos/util/torch_functions.py
rlgym_learn_algos/util/torch_pydantic.py
rlgym_learn_algos-0.2.6.dist-info/METADATA
rlgym_learn_algos-0.2.6.dist-info/WHEEL
rlgym_learn_algos-0.2.6.dist-info/licenses/LICENSE
rlgym_learn_algos-0.2.6.dist-info/RECORD
