Metadata-Version: 2.4
Name: rlgym-learn-algos
Version: 0.2.6
Classifier: Programming Language :: Rust
Classifier: Programming Language :: Python :: Implementation :: CPython
Requires-Dist: pydantic>=2.8.2
Requires-Dist: numpy>1.21
Requires-Dist: torch>1.13
Requires-Dist: typing-extensions>4.6
Requires-Dist: rlgym>=2.0.0
Requires-Dist: rlgym-learn>=0.1.7
Requires-Dist: wandb>0.15 ; extra == 'wandb'
Provides-Extra: wandb
License-File: LICENSE
Summary: Algorithm implementations for rlgym-learn
Keywords: rocket-league,gym,reinforcement-learning,simulation,ppo,rlgym,rocketsim
Author: Jonathan Keegan
License: Apache-2.0
Requires-Python: >=3.8, <3.13
Project-URL: Issues, https://github.com/JPK314/rlgym-learn-algos/issues
Project-URL: Repository, https://github.com/JPK314/rlgym-learn-algos.git
